openvasreporting/__init__.py
openvasreporting/__main__.py
openvasreporting/openvasreporting.py
openvasreporting/libs/__init__.py
openvasreporting/libs/config.py
openvasreporting/libs/export.py
openvasreporting/libs/parsed_data.py
openvasreporting/libs/parser.py
openvasreporting/src/openvas-template.docx
OpenVAS_Reporting-1.6.1.dist-info/LICENSE
OpenVAS_Reporting-1.6.1.dist-info/METADATA
OpenVAS_Reporting-1.6.1.dist-info/WHEEL
OpenVAS_Reporting-1.6.1.dist-info/entry_points.txt
OpenVAS_Reporting-1.6.1.dist-info/top_level.txt
OpenVAS_Reporting-1.6.1.dist-info/RECORD
