Metadata-Version: 2.1
Name: OpenVAS-Reporting
Version: 1.6.1
Summary: A tool to convert OpenVAS XML into reports.
Home-page: https://github.com/TheGroundZero/openvasreporting
Author: TheGroundZero (@DezeStijn)
Author-email: 2406013+TheGroundZero@users.noreply.github.com
Maintainer: Eduardo Ferreira (@dudacgf)
License: GPL-3.0-or-later
Project-URL: Source Code, https://github.com/TheGroundZero/openvasreporting
Project-URL: Documentation, https://openvas-reporting.sequr.be
Project-URL: Issues, https://github.com/TheGroundZero/openvasreporting/issues/
Keywords: OpenVAS OpenVAS-reports Excel xlsxwriter xlsx reporting reports report
Classifier: Development Status :: 5 - Production/Stable
Classifier: Environment :: Console
Classifier: Framework :: Sphinx
Classifier: Intended Audience :: Developers
Classifier: Intended Audience :: End Users/Desktop
Classifier: Intended Audience :: Information Technology
Classifier: Intended Audience :: Other Audience
Classifier: Intended Audience :: System Administrators
Classifier: License :: OSI Approved :: GNU General Public License v3 or later (GPLv3+)
Classifier: Natural Language :: English
Classifier: Operating System :: MacOS
Classifier: Operating System :: Microsoft :: Windows
Classifier: Operating System :: POSIX
Classifier: Operating System :: Unix
Classifier: Programming Language :: Python
Classifier: Topic :: Documentation :: Sphinx
Classifier: Topic :: Internet :: Log Analysis
Classifier: Topic :: Security
Requires-Python: >=3.12
License-File: LICENSE
Requires-Dist: xlsxwriter >=1.0.0
Requires-Dist: python-docx >=0.8.7
Requires-Dist: matplotlib >=2.2.2
Requires-Dist: netaddr >=0.8.0
